{
	"Material::version": 0,
	"transparent": false,
	"shadow": true,
	"program": {
		"ShaderProgram::version": 0,
		"shaders": [
			{
				"Shader::version": 0,
				"type": 0,
				"path": "shaders/sector/std_v.glsl",
				"defines": []
			},
			{
				"Shader::version": 0,
				"type": 2,
				"path": "shaders/sector/std_f.glsl",
				"defines": []
			}
		]
	},
	"textures": [
		"images/tile/diffuse/null.png",
		"images/tile/normal/null.png",
		"images/tile/fx/empty.png"
	],
	"glowTextures": [],
	"cubemaps": [
		"images/cubemap/tile/cubemap.json"
	]
}